{
  "items": [
    {
      "id": "zaamatic",
      "name": "Zaamatic",
      "category": "Flower",
      "subcategory": "CA$$H RULE$",
      "sale": false,
      "pricingType": "By Size (3.5/7/14/28)",
      "prices": { "g3_5": 30, "g7": 50, "g14": 100, "g28": 180 },
      "availability": { "g3_5": true, "g7": true, "g14": true, "g28": true },
      "description": "",
      "effects": ["RELAXED", "BODY BUZZ", "CALM", "STRESS RELIEF"],
      "image": "images/Zaamatic.JPG"
    },

    {
      "id": "double-bubble",
      "name": "Double bubble",
      "category": "Flower",
      "subcategory": "LOOSE LINEUP",
      "sale": false,
      "pricingType": "By Size (3.5/7/14/28)",
      "prices": { "g3_5": 30, "g7": 50, "g14": 100, "g28": 180 },
      "availability": { "g3_5": true, "g7": true, "g14": true, "g28": true },
      "description": "",
      "effects": [],
      "image": "images/Double-bubble.png"
    },
    {
      "id": "pink-certz",
      "name": "Pink certz",
      "category": "Flower",
      "subcategory": "LOOSE LINEUP",
      "sale": false,
      "pricingType": "By Size (3.5/7/14/28)",
      "prices": { "g3_5": 25, "g7": 45, "g14": 90, "g28": 160 },
      "availability": { "g3_5": true, "g7": true, "g14": true, "g28": true },
      "description": "",
      "effects": [],
      "image": "images/Pink-Certz.png"
    },
    {
      "id": "space-candy",
      "name": "Space candy",
      "category": "Flower",
      "subcategory": "LOOSE LINEUP",
      "sale": false,
      "pricingType": "By Size (3.5/7/14/28)",
      "prices": { "g3_5": 25, "g7": 45, "g14": 90, "g28": 160 },
      "availability": { "g3_5": true, "g7": true, "g14": true, "g28": true },
      "description": "",
      "effects": ["CREATIVE", "UPLIFTED", "EUPHORIC", "CLEAR-HEADED"],
      "image": "images/SpaceCandy.JPG"
    },
    {
      "id": "fruit-snacks",
      "name": "Fruit snacks",
      "category": "Flower",
      "subcategory": "LOOSE LINEUP",
      "sale": false,
      "pricingType": "By Size (3.5/7/14/28)",
      "prices": { "g3_5": 25, "g7": 45, "g14": 90, "g28": 160 },
      "availability": { "g3_5": true, "g7": true, "g14": true, "g28": true },
      "description": "",
      "effects": ["HAPPY", "GIGGLY", "UPLIFTED", "RELAXED"],
      "image": "images/FruitStripes.JPG"
    },
    {
      "id": "silver-back-gorilla",
      "name": "Silver back gorilla",
      "category": "Flower",
      "subcategory": "LOOSE LINEUP",
      "sale": false,
      "pricingType": "By Size (3.5/7/14/28)",
      "prices": { "g3_5": 25, "g7": 45, "g14": 90, "g28": 160 },
      "availability": { "g3_5": true, "g7": true, "g14": true, "g28": true },
      "description": "",
      "effects": ["HEAVY BODY", "COUCH-LOCK", "CALM", "SLEEPY"],
      "image": "images/SilverBackGorilla.jpg"
    },
    {
      "id": "bubblegum-poppers",
      "name": "Bubblegum poppers",
      "category": "Flower",
      "subcategory": "LOOSE LINEUP",
      "sale": false,
      "pricingType": "By Size (3.5/7/14/28)",
      "prices": { "g3_5": 25, "g7": 45, "g14": 90, "g28": 160 },
      "availability": { "g3_5": true, "g7": true, "g14": true, "g28": true },
      "description": "",
      "effects": ["CREATIVE", "SOCIAL", "HAPPY", "UPLIFTED"],
      "image": "images/BubbleGumPoppers.jpg"
    },
    {
      "id": "sherbert",
      "name": "Sherbert",
      "category": "Flower",
      "subcategory": "LOOSE LINEUP",
      "sale": false,
      "pricingType": "By Size (3.5/7/14/28)",
      "prices": { "g3_5": 25, "g7": 40, "g14": 80, "g28": 140 },
      "availability": { "g3_5": true, "g7": true, "g14": true, "g28": true },
      "description": "",
      "effects": ["CALM", "RELAXED", "EUPHORIC", "BODY BUZZ"],
      "image": "images/Sherbet.JPG"
    },
    {
      "id": "pink-cadillac",
      "name": "Pink Cadillac",
      "category": "Flower",
      "subcategory": "LOOSE LINEUP",
      "sale": false,
      "pricingType": "By Size (3.5/7/14/28)",
      "prices": { "g3_5": 25, "g7": 40, "g14": 80, "g28": 140 },
      "availability": { "g3_5": true, "g7": true, "g14": true, "g28": true },
      "description": "",
      "effects": ["RELAXED", "CALM", "HAPPY", "BODY BUZZ"],
      "image": "images/PinkCadillac.jpg"
    },
    {
      "id": "candy-fumez-shake",
      "name": "Candy fumez (exotic shake)",
      "category": "Flower",
      "subcategory": "LOOSE LINEUP",
      "sale": false,
      "pricingType": "By Size (3.5/7/14/28)",
      "prices": { "g3_5": 30, "g7": 45, "g14": 80, "g28": 150 },
      "availability": { "g3_5": true, "g7": true, "g14": true, "g28": true },
      "description": "",
      "effects": ["UPLIFTED", "EUPHORIC", "CREATIVE", "RELAXED"],
      "image": "images/CandyFumesShake.jpg"
    },
    {
      "id": "sherb-candy-shake",
      "name": "Sherb candy (shake)",
      "category": "Flower",
      "subcategory": "LOOSE LINEUP",
      "sale": false,
      "pricingType": "By Size (3.5/7/14/28)",
      "prices": { "g3_5": 25, "g7": 40, "g14": 60, "g28": 100 },
      "availability": { "g3_5": true, "g7": true, "g14": true, "g28": true },
      "description": "",
      "effects": ["CALM", "HAPPY", "RELAXED", "MUNCHIES"],
      "image": "images/SherbCandyShake.jpg"
    },

    {
      "id": "rosin-budder",
      "name": "Rosin Budder",
      "category": "Concentrates",
      "subcategory": "Concentrates",
      "sale": false,
      "pricingType": "Per Gram",
      "prices": { "perGram": 30 },
      "availability": { "perGram": true },
      "description": "",
      "effects": ["EUPHORIC", "RELAXED", "TINGLY", "HEAVY BODY"],
      "image": "images/RosinBudder.JPG"
    },

    {
      "id": "bbl-havana-pearls-cigars",
      "name": "BBL Havana Pearls Cigars",
      "category": "Accessories",
      "subcategory": "Cigars",
      "sale": false,
      "pricingType": "Single Price",
      "prices": { "single": 3 },
      "availability": { "single": true },
      "description": "",
      "image": ""
    },
    {
      "id": "brother-broad-leaf-barrel-series-havana-cigars",
      "name": "Brother Broad Leaf Barrel Series Havana Cigars",
      "category": "Accessories",
      "subcategory": "Cigars",
      "sale": false,
      "pricingType": "Single Price",
      "prices": { "single": 3 },
      "availability": { "single": true },
      "description": "",
      "image": ""
    },
    {
      "id": "elements-rice-rolling-papers",
      "name": "Elements Rice Rolling Papers",
      "category": "Accessories",
      "subcategory": "Rolling Papers",
      "sale": false,
      "pricingType": "Single Price",
      "prices": { "single": 3 },
      "availability": { "single": true },
      "description": "",
      "image": ""
    },
    {
      "id": "elements-phantom-papers",
      "name": "Elements Phantom Papers",
      "category": "Accessories",
      "subcategory": "Rolling Papers",
      "sale": false,
      "pricingType": "Single Price",
      "prices": { "single": 4 },
      "availability": { "single": true },
      "description": "",
      "image": ""
    },
    {
      "id": "bic-lighter",
      "name": "Bic Lighter",
      "category": "Accessories",
      "subcategory": "Lighters & Tips",
      "sale": false,
      "pricingType": "Single Price",
      "prices": { "single": 3 },
      "availability": { "single": true },
      "description": "",
      "image": ""
    },
    {
      "id": "raw-rolling-tips",
      "name": "RAW Rolling Tips",
      "category": "Accessories",
      "subcategory": "Lighters & Tips",
      "sale": false,
      "pricingType": "Single Price",
      "prices": { "single": 1 },
      "availability": { "single": true },
      "description": "",
      "image": ""
    }
  ]
}
